odoo/addons/l10n_ro_account_bank_statement_report/README.rst
odoo/addons/l10n_ro_account_bank_statement_report/__init__.py
odoo/addons/l10n_ro_account_bank_statement_report/__manifest__.py
odoo/addons/l10n_ro_account_bank_statement_report/i18n/l10n_ro_account_bank_statement_report.pot
odoo/addons/l10n_ro_account_bank_statement_report/i18n/ro.po
odoo/addons/l10n_ro_account_bank_statement_report/models/__init__.py
odoo/addons/l10n_ro_account_bank_statement_report/models/account_bank_statement.py
odoo/addons/l10n_ro_account_bank_statement_report/readme/CONTRIBUTORS.md
odoo/addons/l10n_ro_account_bank_statement_report/readme/DESCRIPTION.md
odoo/addons/l10n_ro_account_bank_statement_report/readme/INSTALL.md
odoo/addons/l10n_ro_account_bank_statement_report/readme/USAGE.md
odoo/addons/l10n_ro_account_bank_statement_report/static/description/icon.png
odoo/addons/l10n_ro_account_bank_statement_report/static/description/icon.svg
odoo/addons/l10n_ro_account_bank_statement_report/static/description/index.html
odoo/addons/l10n_ro_account_bank_statement_report/views/report_l10n_ro_statement_daily.xml
odoo/addons/l10n_ro_account_bank_statement_report/views/report_l10n_ro_statement_period.xml
odoo/addons/l10n_ro_account_bank_statement_report/views/report_statement.xml
odoo_addon_l10n_ro_account_bank_statement_report-18.0.0.1.0.1.dist-info/METADATA
odoo_addon_l10n_ro_account_bank_statement_report-18.0.0.1.0.1.dist-info/WHEEL
odoo_addon_l10n_ro_account_bank_statement_report-18.0.0.1.0.1.dist-info/top_level.txt
odoo_addon_l10n_ro_account_bank_statement_report-18.0.0.1.0.1.dist-info/RECORD
